text2term/__init__.py
text2term/__main__.py
text2term/bioportal_mapper.py
text2term/mapper.py
text2term/onto_cache.py
text2term/onto_utils.py
text2term/preprocess.py
text2term/syntactic_mapper.py
text2term/t2t.py
text2term/tagged_term.py
text2term/term.py
text2term/term_collector.py
text2term/term_graph.py
text2term/term_graph_generator.py
text2term/term_mapping.py
text2term/tfidf_mapper.py
text2term/zooma_mapper.py
text2term-4.5.0.dist-info/licenses/LICENSE
text2term-4.5.0.dist-info/METADATA
text2term-4.5.0.dist-info/WHEEL
text2term-4.5.0.dist-info/top_level.txt
text2term-4.5.0.dist-info/RECORD
