Metadata-Version: 2.4
Name: text2term
Version: 4.5.0
Summary: A tool for mapping free-text descriptions of entities to ontology terms
Author-email: Rafael Goncalves <goncalves@stanford.edu>, Jason Payne <paynejason@gmail.com>
Maintainer-email: Rafael Goncalves <goncalves@stanford.edu>
License-Expression: MIT
Project-URL: Homepage, https://github.com/rsgoncalves/text2term
Project-URL: Repository, https://github.com/rsgoncalves/text2term.git
Project-URL: Issues, https://github.com/rsgoncalves/text2term/issues
Keywords: ontology,text mining,mapping,biomedical
Classifier: Development Status :: 4 - Beta
Classifier: Intended Audience :: Science/Research
Classifier: Topic :: Scientific/Engineering
Classifier: Programming Language :: Python :: 3
Classifier: Operating System :: OS Independent
Classifier: Environment :: Console
Requires-Python: >=3.9
License-File: LICENSE
Requires-Dist: owlready2~=0.47
Requires-Dist: argparse~=1.4.0
Requires-Dist: pandas~=2.2.3
Requires-Dist: numpy~=1.26.4
Requires-Dist: gensim~=4.3.2
Requires-Dist: scipy~=1.12.0
Requires-Dist: scikit-learn~=1.6.1
Requires-Dist: setuptools~=80.8.0
Requires-Dist: requests~=2.32.3
Requires-Dist: tqdm~=4.67.1
Requires-Dist: sparse-dot-topn~=1.1.3
Requires-Dist: bioregistry~=0.11.10
Requires-Dist: nltk~=3.9.1
Requires-Dist: rapidfuzz~=3.12.2
Requires-Dist: shortuuid~=1.0.11
Requires-Dist: myst-parser~=4.0.1
Provides-Extra: dev
Requires-Dist: pytest==8.1.1; extra == "dev"
Provides-Extra: docs
Requires-Dist: sphinx; extra == "docs"
Dynamic: license-file
